{
  "id": "ea97438f-e3da-48af-8cba-224f26087039",
  "prevId": "00000000-0000-0000-0000-000000000000",
  "version": "7",
  "dialect": "postgresql",
  "tables": {
    "public.achievements": {
      "name": "achievements",
      "schema": "",
      "columns": {
        "id": {
          "name": "id",
          "type": "uuid",
          "primaryKey": true,
          "notNull": true,
          "default": "gen_random_uuid()"
        },
        "user_id": {
          "name": "user_id",
          "type": "uuid",
          "primaryKey": false,
          "notNull": true
        },
        "badge_id": {
          "name": "badge_id",
          "type": "varchar(100)",
          "primaryKey": false,
          "notNull": true
        },
        "earned_at": {
          "name": "earned_at",
          "type": "timestamp with time zone",
          "primaryKey": false,
          "notNull": true,
          "default": "now()"
        }
      },
      "indexes": {},
      "foreignKeys": {
        "achievements_user_id_users_id_fk": {
          "name": "achievements_user_id_users_id_fk",
          "tableFrom": "achievements",
          "tableTo": "users",
          "columnsFrom": [
            "user_id"
          ],
          "columnsTo": [
            "id"
          ],
          "onDelete": "cascade",
          "onUpdate": "no action"
        }
      },
      "compositePrimaryKeys": {},
      "uniqueConstraints": {},
      "policies": {},
      "checkConstraints": {},
      "isRLSEnabled": false
    },
    "public.ai_interactions": {
      "name": "ai_interactions",
      "schema": "",
      "columns": {
        "id": {
          "name": "id",
          "type": "uuid",
          "primaryKey": true,
          "notNull": true,
          "default": "gen_random_uuid()"
        },
        "user_id": {
          "name": "user_id",
          "type": "uuid",
          "primaryKey": false,
          "notNull": true
        },
        "interaction_type": {
          "name": "interaction_type",
          "type": "varchar(100)",
          "primaryKey": false,
          "notNull": true
        },
        "input_text": {
          "name": "input_text",
          "type": "text",
          "primaryKey": false,
          "notNull": false
        },
        "output_text": {
          "name": "output_text",
          "type": "text",
          "primaryKey": false,
          "notNull": false
        },
        "model_used": {
          "name": "model_used",
          "type": "varchar(100)",
          "primaryKey": false,
          "notNull": false
        },
        "tokens_input": {
          "name": "tokens_input",
          "type": "integer",
          "primaryKey": false,
          "notNull": false
        },
        "tokens_output": {
          "name": "tokens_output",
          "type": "integer",
          "primaryKey": false,
          "notNull": false
        },
        "cached": {
          "name": "cached",
          "type": "boolean",
          "primaryKey": false,
          "notNull": false,
          "default": false
        },
        "cost_usd": {
          "name": "cost_usd",
          "type": "numeric(10, 6)",
          "primaryKey": false,
          "notNull": false
        },
        "created_at": {
          "name": "created_at",
          "type": "timestamp with time zone",
          "primaryKey": false,
          "notNull": true,
          "default": "now()"
        }
      },
      "indexes": {},
      "foreignKeys": {
        "ai_interactions_user_id_users_id_fk": {
          "name": "ai_interactions_user_id_users_id_fk",
          "tableFrom": "ai_interactions",
          "tableTo": "users",
          "columnsFrom": [
            "user_id"
          ],
          "columnsTo": [
            "id"
          ],
          "onDelete": "cascade",
          "onUpdate": "no action"
        }
      },
      "compositePrimaryKeys": {},
      "uniqueConstraints": {},
      "policies": {},
      "checkConstraints": {},
      "isRLSEnabled": false
    },
    "public.clients": {
      "name": "clients",
      "schema": "",
      "columns": {
        "id": {
          "name": "id",
          "type": "uuid",
          "primaryKey": true,
          "notNull": true,
          "default": "gen_random_uuid()"
        },
        "user_id": {
          "name": "user_id",
          "type": "uuid",
          "primaryKey": false,
          "notNull": true
        },
        "company_name": {
          "name": "company_name",
          "type": "varchar(255)",
          "primaryKey": false,
          "notNull": true
        },
        "website": {
          "name": "website",
          "type": "text",
          "primaryKey": false,
          "notNull": false
        },
        "industry": {
          "name": "industry",
          "type": "varchar(100)",
          "primaryKey": false,
          "notNull": false
        },
        "research_data": {
          "name": "research_data",
          "type": "jsonb",
          "primaryKey": false,
          "notNull": false
        },
        "pipeline_stage": {
          "name": "pipeline_stage",
          "type": "pipeline_stage",
          "typeSchema": "public",
          "primaryKey": false,
          "notNull": true,
          "default": "'lead'"
        },
        "deal_value": {
          "name": "deal_value",
          "type": "numeric(12, 2)",
          "primaryKey": false,
          "notNull": false
        },
        "last_contact_at": {
          "name": "last_contact_at",
          "type": "timestamp with time zone",
          "primaryKey": false,
          "notNull": false
        },
        "next_follow_up_at": {
          "name": "next_follow_up_at",
          "type": "timestamp with time zone",
          "primaryKey": false,
          "notNull": false
        },
        "notes": {
          "name": "notes",
          "type": "text",
          "primaryKey": false,
          "notNull": false
        },
        "created_at": {
          "name": "created_at",
          "type": "timestamp with time zone",
          "primaryKey": false,
          "notNull": true,
          "default": "now()"
        },
        "updated_at": {
          "name": "updated_at",
          "type": "timestamp with time zone",
          "primaryKey": false,
          "notNull": true,
          "default": "now()"
        }
      },
      "indexes": {},
      "foreignKeys": {
        "clients_user_id_users_id_fk": {
          "name": "clients_user_id_users_id_fk",
          "tableFrom": "clients",
          "tableTo": "users",
          "columnsFrom": [
            "user_id"
          ],
          "columnsTo": [
            "id"
          ],
          "onDelete": "cascade",
          "onUpdate": "no action"
        }
      },
      "compositePrimaryKeys": {},
      "uniqueConstraints": {},
      "policies": {},
      "checkConstraints": {},
      "isRLSEnabled": false
    },
    "public.coach_sessions": {
      "name": "coach_sessions",
      "schema": "",
      "columns": {
        "id": {
          "name": "id",
          "type": "uuid",
          "primaryKey": true,
          "notNull": true,
          "default": "gen_random_uuid()"
        },
        "user_id": {
          "name": "user_id",
          "type": "uuid",
          "primaryKey": false,
          "notNull": true
        },
        "scenario": {
          "name": "scenario",
          "type": "varchar(200)",
          "primaryKey": false,
          "notNull": true
        },
        "conversation": {
          "name": "conversation",
          "type": "jsonb",
          "primaryKey": false,
          "notNull": true,
          "default": "'[]'::jsonb"
        },
        "score": {
          "name": "score",
          "type": "integer",
          "primaryKey": false,
          "notNull": false
        },
        "feedback": {
          "name": "feedback",
          "type": "text",
          "primaryKey": false,
          "notNull": false
        },
        "duration_seconds": {
          "name": "duration_seconds",
          "type": "integer",
          "primaryKey": false,
          "notNull": false
        },
        "created_at": {
          "name": "created_at",
          "type": "timestamp with time zone",
          "primaryKey": false,
          "notNull": true,
          "default": "now()"
        }
      },
      "indexes": {},
      "foreignKeys": {
        "coach_sessions_user_id_users_id_fk": {
          "name": "coach_sessions_user_id_users_id_fk",
          "tableFrom": "coach_sessions",
          "tableTo": "users",
          "columnsFrom": [
            "user_id"
          ],
          "columnsTo": [
            "id"
          ],
          "onDelete": "cascade",
          "onUpdate": "no action"
        }
      },
      "compositePrimaryKeys": {},
      "uniqueConstraints": {},
      "policies": {},
      "checkConstraints": {},
      "isRLSEnabled": false
    },
    "public.daily_tasks": {
      "name": "daily_tasks",
      "schema": "",
      "columns": {
        "id": {
          "name": "id",
          "type": "uuid",
          "primaryKey": true,
          "notNull": true,
          "default": "gen_random_uuid()"
        },
        "user_id": {
          "name": "user_id",
          "type": "uuid",
          "primaryKey": false,
          "notNull": true
        },
        "task_type": {
          "name": "task_type",
          "type": "varchar(100)",
          "primaryKey": false,
          "notNull": true
        },
        "description": {
          "name": "description",
          "type": "text",
          "primaryKey": false,
          "notNull": true
        },
        "target_client_id": {
          "name": "target_client_id",
          "type": "uuid",
          "primaryKey": false,
          "notNull": false
        },
        "xp_reward": {
          "name": "xp_reward",
          "type": "integer",
          "primaryKey": false,
          "notNull": true,
          "default": 10
        },
        "status": {
          "name": "status",
          "type": "daily_task_status",
          "typeSchema": "public",
          "primaryKey": false,
          "notNull": true,
          "default": "'pending'"
        },
        "date": {
          "name": "date",
          "type": "date",
          "primaryKey": false,
          "notNull": true
        },
        "created_at": {
          "name": "created_at",
          "type": "timestamp with time zone",
          "primaryKey": false,
          "notNull": true,
          "default": "now()"
        }
      },
      "indexes": {},
      "foreignKeys": {
        "daily_tasks_user_id_users_id_fk": {
          "name": "daily_tasks_user_id_users_id_fk",
          "tableFrom": "daily_tasks",
          "tableTo": "users",
          "columnsFrom": [
            "user_id"
          ],
          "columnsTo": [
            "id"
          ],
          "onDelete": "cascade",
          "onUpdate": "no action"
        },
        "daily_tasks_target_client_id_clients_id_fk": {
          "name": "daily_tasks_target_client_id_clients_id_fk",
          "tableFrom": "daily_tasks",
          "tableTo": "clients",
          "columnsFrom": [
            "target_client_id"
          ],
          "columnsTo": [
            "id"
          ],
          "onDelete": "set null",
          "onUpdate": "no action"
        }
      },
      "compositePrimaryKeys": {},
      "uniqueConstraints": {},
      "policies": {},
      "checkConstraints": {},
      "isRLSEnabled": false
    },
    "public.follow_ups": {
      "name": "follow_ups",
      "schema": "",
      "columns": {
        "id": {
          "name": "id",
          "type": "uuid",
          "primaryKey": true,
          "notNull": true,
          "default": "gen_random_uuid()"
        },
        "user_id": {
          "name": "user_id",
          "type": "uuid",
          "primaryKey": false,
          "notNull": true
        },
        "client_id": {
          "name": "client_id",
          "type": "uuid",
          "primaryKey": false,
          "notNull": true
        },
        "due_date": {
          "name": "due_date",
          "type": "date",
          "primaryKey": false,
          "notNull": true
        },
        "message_draft": {
          "name": "message_draft",
          "type": "text",
          "primaryKey": false,
          "notNull": false
        },
        "status": {
          "name": "status",
          "type": "follow_up_status",
          "typeSchema": "public",
          "primaryKey": false,
          "notNull": true,
          "default": "'pending'"
        },
        "priority": {
          "name": "priority",
          "type": "priority",
          "typeSchema": "public",
          "primaryKey": false,
          "notNull": true,
          "default": "'medium'"
        },
        "created_at": {
          "name": "created_at",
          "type": "timestamp with time zone",
          "primaryKey": false,
          "notNull": true,
          "default": "now()"
        }
      },
      "indexes": {},
      "foreignKeys": {
        "follow_ups_user_id_users_id_fk": {
          "name": "follow_ups_user_id_users_id_fk",
          "tableFrom": "follow_ups",
          "tableTo": "users",
          "columnsFrom": [
            "user_id"
          ],
          "columnsTo": [
            "id"
          ],
          "onDelete": "cascade",
          "onUpdate": "no action"
        },
        "follow_ups_client_id_clients_id_fk": {
          "name": "follow_ups_client_id_clients_id_fk",
          "tableFrom": "follow_ups",
          "tableTo": "clients",
          "columnsFrom": [
            "client_id"
          ],
          "columnsTo": [
            "id"
          ],
          "onDelete": "cascade",
          "onUpdate": "no action"
        }
      },
      "compositePrimaryKeys": {},
      "uniqueConstraints": {},
      "policies": {},
      "checkConstraints": {},
      "isRLSEnabled": false
    },
    "public.leaderboard_entries": {
      "name": "leaderboard_entries",
      "schema": "",
      "columns": {
        "id": {
          "name": "id",
          "type": "uuid",
          "primaryKey": true,
          "notNull": true,
          "default": "gen_random_uuid()"
        },
        "user_id": {
          "name": "user_id",
          "type": "uuid",
          "primaryKey": false,
          "notNull": true
        },
        "period": {
          "name": "period",
          "type": "varchar(20)",
          "primaryKey": false,
          "notNull": true
        },
        "xp_total": {
          "name": "xp_total",
          "type": "integer",
          "primaryKey": false,
          "notNull": true,
          "default": 0
        },
        "rank": {
          "name": "rank",
          "type": "integer",
          "primaryKey": false,
          "notNull": false
        },
        "created_at": {
          "name": "created_at",
          "type": "timestamp with time zone",
          "primaryKey": false,
          "notNull": true,
          "default": "now()"
        }
      },
      "indexes": {},
      "foreignKeys": {
        "leaderboard_entries_user_id_users_id_fk": {
          "name": "leaderboard_entries_user_id_users_id_fk",
          "tableFrom": "leaderboard_entries",
          "tableTo": "users",
          "columnsFrom": [
            "user_id"
          ],
          "columnsTo": [
            "id"
          ],
          "onDelete": "cascade",
          "onUpdate": "no action"
        }
      },
      "compositePrimaryKeys": {},
      "uniqueConstraints": {},
      "policies": {},
      "checkConstraints": {},
      "isRLSEnabled": false
    },
    "public.outreach_emails": {
      "name": "outreach_emails",
      "schema": "",
      "columns": {
        "id": {
          "name": "id",
          "type": "uuid",
          "primaryKey": true,
          "notNull": true,
          "default": "gen_random_uuid()"
        },
        "user_id": {
          "name": "user_id",
          "type": "uuid",
          "primaryKey": false,
          "notNull": true
        },
        "client_id": {
          "name": "client_id",
          "type": "uuid",
          "primaryKey": false,
          "notNull": true
        },
        "subject": {
          "name": "subject",
          "type": "varchar(500)",
          "primaryKey": false,
          "notNull": true
        },
        "body": {
          "name": "body",
          "type": "text",
          "primaryKey": false,
          "notNull": true
        },
        "language": {
          "name": "language",
          "type": "varchar(10)",
          "primaryKey": false,
          "notNull": false
        },
        "tone": {
          "name": "tone",
          "type": "varchar(50)",
          "primaryKey": false,
          "notNull": false
        },
        "score": {
          "name": "score",
          "type": "integer",
          "primaryKey": false,
          "notNull": false
        },
        "ai_suggestions": {
          "name": "ai_suggestions",
          "type": "jsonb",
          "primaryKey": false,
          "notNull": false
        },
        "status": {
          "name": "status",
          "type": "email_status",
          "typeSchema": "public",
          "primaryKey": false,
          "notNull": true,
          "default": "'draft'"
        },
        "created_at": {
          "name": "created_at",
          "type": "timestamp with time zone",
          "primaryKey": false,
          "notNull": true,
          "default": "now()"
        }
      },
      "indexes": {},
      "foreignKeys": {
        "outreach_emails_user_id_users_id_fk": {
          "name": "outreach_emails_user_id_users_id_fk",
          "tableFrom": "outreach_emails",
          "tableTo": "users",
          "columnsFrom": [
            "user_id"
          ],
          "columnsTo": [
            "id"
          ],
          "onDelete": "cascade",
          "onUpdate": "no action"
        },
        "outreach_emails_client_id_clients_id_fk": {
          "name": "outreach_emails_client_id_clients_id_fk",
          "tableFrom": "outreach_emails",
          "tableTo": "clients",
          "columnsFrom": [
            "client_id"
          ],
          "columnsTo": [
            "id"
          ],
          "onDelete": "cascade",
          "onUpdate": "no action"
        }
      },
      "compositePrimaryKeys": {},
      "uniqueConstraints": {},
      "policies": {},
      "checkConstraints": {},
      "isRLSEnabled": false
    },
    "public.users": {
      "name": "users",
      "schema": "",
      "columns": {
        "id": {
          "name": "id",
          "type": "uuid",
          "primaryKey": true,
          "notNull": true,
          "default": "gen_random_uuid()"
        },
        "email": {
          "name": "email",
          "type": "varchar(255)",
          "primaryKey": false,
          "notNull": true
        },
        "name": {
          "name": "name",
          "type": "varchar(255)",
          "primaryKey": false,
          "notNull": false
        },
        "avatar_url": {
          "name": "avatar_url",
          "type": "text",
          "primaryKey": false,
          "notNull": false
        },
        "locale": {
          "name": "locale",
          "type": "varchar(10)",
          "primaryKey": false,
          "notNull": true,
          "default": "'en'"
        },
        "level": {
          "name": "level",
          "type": "integer",
          "primaryKey": false,
          "notNull": true,
          "default": 1
        },
        "xp": {
          "name": "xp",
          "type": "integer",
          "primaryKey": false,
          "notNull": true,
          "default": 0
        },
        "streak_days": {
          "name": "streak_days",
          "type": "integer",
          "primaryKey": false,
          "notNull": true,
          "default": 0
        },
        "streak_last_date": {
          "name": "streak_last_date",
          "type": "date",
          "primaryKey": false,
          "notNull": false
        },
        "plan": {
          "name": "plan",
          "type": "plan",
          "typeSchema": "public",
          "primaryKey": false,
          "notNull": true,
          "default": "'free'"
        },
        "daily_ai_count": {
          "name": "daily_ai_count",
          "type": "integer",
          "primaryKey": false,
          "notNull": true,
          "default": 0
        },
        "daily_ai_reset_at": {
          "name": "daily_ai_reset_at",
          "type": "timestamp with time zone",
          "primaryKey": false,
          "notNull": false
        },
        "created_at": {
          "name": "created_at",
          "type": "timestamp with time zone",
          "primaryKey": false,
          "notNull": true,
          "default": "now()"
        },
        "updated_at": {
          "name": "updated_at",
          "type": "timestamp with time zone",
          "primaryKey": false,
          "notNull": true,
          "default": "now()"
        }
      },
      "indexes": {},
      "foreignKeys": {},
      "compositePrimaryKeys": {},
      "uniqueConstraints": {
        "users_email_unique": {
          "name": "users_email_unique",
          "nullsNotDistinct": false,
          "columns": [
            "email"
          ]
        }
      },
      "policies": {},
      "checkConstraints": {},
      "isRLSEnabled": false
    },
    "public.visit_logs": {
      "name": "visit_logs",
      "schema": "",
      "columns": {
        "id": {
          "name": "id",
          "type": "uuid",
          "primaryKey": true,
          "notNull": true,
          "default": "gen_random_uuid()"
        },
        "user_id": {
          "name": "user_id",
          "type": "uuid",
          "primaryKey": false,
          "notNull": true
        },
        "client_id": {
          "name": "client_id",
          "type": "uuid",
          "primaryKey": false,
          "notNull": true
        },
        "audio_url": {
          "name": "audio_url",
          "type": "text",
          "primaryKey": false,
          "notNull": false
        },
        "transcript": {
          "name": "transcript",
          "type": "text",
          "primaryKey": false,
          "notNull": false
        },
        "summary": {
          "name": "summary",
          "type": "text",
          "primaryKey": false,
          "notNull": false
        },
        "next_steps": {
          "name": "next_steps",
          "type": "text[]",
          "primaryKey": false,
          "notNull": false
        },
        "deal_probability": {
          "name": "deal_probability",
          "type": "integer",
          "primaryKey": false,
          "notNull": false
        },
        "client_mood": {
          "name": "client_mood",
          "type": "client_mood",
          "typeSchema": "public",
          "primaryKey": false,
          "notNull": false
        },
        "visit_date": {
          "name": "visit_date",
          "type": "date",
          "primaryKey": false,
          "notNull": true
        },
        "created_at": {
          "name": "created_at",
          "type": "timestamp with time zone",
          "primaryKey": false,
          "notNull": true,
          "default": "now()"
        }
      },
      "indexes": {},
      "foreignKeys": {
        "visit_logs_user_id_users_id_fk": {
          "name": "visit_logs_user_id_users_id_fk",
          "tableFrom": "visit_logs",
          "tableTo": "users",
          "columnsFrom": [
            "user_id"
          ],
          "columnsTo": [
            "id"
          ],
          "onDelete": "cascade",
          "onUpdate": "no action"
        },
        "visit_logs_client_id_clients_id_fk": {
          "name": "visit_logs_client_id_clients_id_fk",
          "tableFrom": "visit_logs",
          "tableTo": "clients",
          "columnsFrom": [
            "client_id"
          ],
          "columnsTo": [
            "id"
          ],
          "onDelete": "cascade",
          "onUpdate": "no action"
        }
      },
      "compositePrimaryKeys": {},
      "uniqueConstraints": {},
      "policies": {},
      "checkConstraints": {},
      "isRLSEnabled": false
    }
  },
  "enums": {
    "public.client_mood": {
      "name": "client_mood",
      "schema": "public",
      "values": [
        "positive",
        "neutral",
        "negative",
        "interested"
      ]
    },
    "public.daily_task_status": {
      "name": "daily_task_status",
      "schema": "public",
      "values": [
        "pending",
        "completed",
        "skipped"
      ]
    },
    "public.email_status": {
      "name": "email_status",
      "schema": "public",
      "values": [
        "draft",
        "sent",
        "replied"
      ]
    },
    "public.follow_up_status": {
      "name": "follow_up_status",
      "schema": "public",
      "values": [
        "pending",
        "done",
        "snoozed"
      ]
    },
    "public.pipeline_stage": {
      "name": "pipeline_stage",
      "schema": "public",
      "values": [
        "lead",
        "contacted",
        "meeting",
        "proposal",
        "negotiation",
        "closed_won",
        "closed_lost"
      ]
    },
    "public.plan": {
      "name": "plan",
      "schema": "public",
      "values": [
        "free",
        "pro",
        "team"
      ]
    },
    "public.priority": {
      "name": "priority",
      "schema": "public",
      "values": [
        "high",
        "medium",
        "low"
      ]
    }
  },
  "schemas": {},
  "sequences": {},
  "roles": {},
  "policies": {},
  "views": {},
  "_meta": {
    "columns": {},
    "schemas": {},
    "tables": {}
  }
}